trajectory/__init__.py
trajectory/handlers.py
trajectory/trajectory_config.yaml
trajectory/test/logging__init__.py
trajectory/test/logging_handlers.py
trajectory/test/test_handlers.py
trajectory/test/test_log.py
shihua_trajectory-0.1.dist-info/LICENSE
shihua_trajectory-0.1.dist-info/METADATA
shihua_trajectory-0.1.dist-info/WHEEL
shihua_trajectory-0.1.dist-info/top_level.txt
shihua_trajectory-0.1.dist-info/RECORD
