Metadata-Version: 2.1
Name: shihua-trajectory
Version: 0.1
Summary: Trajectory is a python toolkit for log management, which supports mongo log forwarding.
Home-page: https://github.com/redblue0216/Trajectory
Author: shihua
Author-email: 15021408795@163.com
License: MIT
Platform: UNKNOWN
Requires-Python: >=3.9.12
License-File: LICENSE
